{
  "version": 1,
  "scopeKey": "pickleball:iloilo:dumangas",
  "createdAt": "2026-03-10T11:17:01.160Z",
  "updatedAt": "2026-03-10T11:18:27.802Z",
  "scope": {
    "provinceSlug": "iloilo",
    "citySlug": "dumangas",
    "provinceName": "Iloilo",
    "cityName": "Dumangas",
    "sportSlug": "pickleball"
  },
  "importedPlaceIds": [],
  "stages": {
    "discovery": {
      "status": "completed",
      "startedAt": "2026-03-10T11:17:01.195Z",
      "finishedAt": "2026-03-10T11:17:28.946Z",
      "lastError": null,
      "notes": "runner executed discovery"
    },
    "scrape": {
      "status": "completed",
      "startedAt": "2026-03-10T11:17:28.946Z",
      "finishedAt": "2026-03-10T11:17:57.209Z",
      "lastError": null,
      "notes": "runner executed scrape"
    },
    "duplicatePreflight": {
      "status": "completed",
      "startedAt": "2026-03-10T11:17:57.210Z",
      "finishedAt": "2026-03-10T11:18:27.204Z",
      "lastError": null,
      "notes": "runner executed duplicate preflight"
    },
    "importApproved": {
      "status": "skipped",
      "startedAt": "2026-03-10T11:18:27.776Z",
      "finishedAt": "2026-03-10T11:18:27.802Z",
      "lastError": null,
      "notes": "all approved rows were out of scope for dumangas, skipped 1"
    },
    "facebookDiscovery": {
      "status": "pending",
      "startedAt": null,
      "finishedAt": null,
      "lastError": null,
      "notes": null
    },
    "facebookCapture": {
      "status": "pending",
      "startedAt": null,
      "finishedAt": null,
      "lastError": null,
      "notes": null
    },
    "facebookDuplicatePreflight": {
      "status": "pending",
      "startedAt": null,
      "finishedAt": null,
      "lastError": null,
      "notes": null
    },
    "facebookImportApproved": {
      "status": "pending",
      "startedAt": null,
      "finishedAt": null,
      "lastError": null,
      "notes": null
    },
    "dbVerification": {
      "status": "skipped",
      "startedAt": null,
      "finishedAt": "2026-03-10T11:18:27.802Z",
      "lastError": null,
      "notes": "all approved rows were out of scope for dumangas"
    },
    "embeddingBackfill": {
      "status": "skipped",
      "startedAt": null,
      "finishedAt": "2026-03-10T11:18:27.802Z",
      "lastError": null,
      "notes": "all approved rows were out of scope"
    }
  }
}
