{
  "version": 1,
  "scopeKey": "facebook:pickleball:negros-oriental:bayawan-city-tulong",
  "createdAt": "2026-03-10T15:26:34.444Z",
  "updatedAt": "2026-03-10T15:26:44.280Z",
  "queries": [
    "site:facebook.com pickleball Bayawan City (Tulong) Negros Oriental",
    "site:facebook.com \"Bayawan City (Tulong)\" \"Negros Oriental\" \"pickleball\"",
    "site:facebook.com \"Bayawan City (Tulong)\" \"pickleball club\"",
    "site:facebook.com \"Bayawan City (Tulong)\" \"pickleball court\"",
    "site:facebook.com \"Negros Oriental\" \"pickleball\""
  ],
  "urls": {
    "https://facebook.com/rotarycluboftolong/posts/1st-rotary-club-of-tolong-pickleball-tournament-for-a-causedink-for-pink-for-bre/1255900456580048": {
      "canonicalUrl": "https://facebook.com/rotarycluboftolong/posts/1st-rotary-club-of-tolong-pickleball-tournament-for-a-causedink-for-pink-for-bre/1255900456580048",
      "latestUrl": "https://www.facebook.com/rotarycluboftolong/posts/1st-rotary-club-of-tolong-pickleball-tournament-for-a-causedink-for-pink-for-bre/1255900456580048/",
      "firstDiscoveredAt": "2026-03-10T15:26:34.444Z",
      "lastDiscoveredAt": "2026-03-10T15:26:34.444Z",
      "sourceQuery": "site:facebook.com pickleball Bayawan City (Tulong) Negros Oriental",
      "title": "1st ROTARY CLUB OF TOLONG PICKLEBALL TOURNAMENT FOR ...",
      "snippet": "Thank you Bayawan City Pickleball Club for everything you have done to make the event a success.From day 1 till awarding you carried it through. Barangays Suba ...",
      "domain": "facebook.com",
      "relevanceScore": 10,
      "handedOffToScrapeAt": null
    },
    "https://cs-cz.facebook.com/rotarycluboftolong": {
      "canonicalUrl": "https://cs-cz.facebook.com/rotarycluboftolong",
      "latestUrl": "https://cs-cz.facebook.com/rotarycluboftolong/",
      "firstDiscoveredAt": "2026-03-10T15:26:34.444Z",
      "lastDiscoveredAt": "2026-03-10T15:26:34.444Z",
      "sourceQuery": "site:facebook.com pickleball Bayawan City (Tulong) Negros Oriental",
      "title": "Rotary Club of Tolong (@rotarycluboftolong) • Facebook",
      "snippet": "The ROTARY CLUB OF TOLONG together with the Bayawan City Pickleball Club, Barangay Suba and Barangay Poblacion invites you to: DINK FOR PINK A Pickleball ...",
      "domain": "facebook.com",
      "relevanceScore": 13,
      "handedOffToScrapeAt": "2026-03-10T15:26:34.444Z"
    },
    "https://facebook.com/groups/142896755886772/posts/3547690368740710": {
      "canonicalUrl": "https://facebook.com/groups/142896755886772/posts/3547690368740710",
      "latestUrl": "https://www.facebook.com/groups/142896755886772/posts/3547690368740710/",
      "firstDiscoveredAt": "2026-03-10T15:26:34.444Z",
      "lastDiscoveredAt": "2026-03-10T15:26:34.444Z",
      "sourceQuery": "site:facebook.com pickleball Bayawan City (Tulong) Negros Oriental",
      "title": "Bayawan City, Negros Oriental - Facebook",
      "snippet": "NEW PICKLE BALL TSHIRT DESIGN Check out now ‼️ Pickleball OneMoreGame Full Sublimation T-Shirt | Shopee Philippines. S.SHOPEE.PH.",
      "domain": "facebook.com",
      "relevanceScore": 10,
      "handedOffToScrapeAt": null
    },
    "https://facebook.com/rotaractcluboftolong": {
      "canonicalUrl": "https://facebook.com/rotaractcluboftolong",
      "latestUrl": "https://www.facebook.com/rotaractcluboftolong/",
      "firstDiscoveredAt": "2026-03-10T15:26:34.444Z",
      "lastDiscoveredAt": "2026-03-10T15:26:34.444Z",
      "sourceQuery": "site:facebook.com pickleball Bayawan City (Tulong) Negros Oriental",
      "title": "Rotaract Club Of Tolong - Bayawan City (@rotaractcluboftolong)",
      "snippet": "❣️ 1st Rotary Club of Tolong Pickleball Tournament for a Cause! ... City, Negros Oriental. Nov 17, 2025󰞋󱟠. 󳄫. ☺Tulong para sa Canlaon: 2nd ...",
      "domain": "facebook.com",
      "relevanceScore": 15,
      "handedOffToScrapeAt": "2026-03-10T15:26:34.444Z"
    },
    "https://facebook.com/photo.php?fbid=1260565579439129&set=a.455553306607031&type=3": {
      "canonicalUrl": "https://facebook.com/photo.php?fbid=1260565579439129&set=a.455553306607031&type=3",
      "latestUrl": "https://www.facebook.com/photo.php?fbid=1260565579439129&set=a.455553306607031&type=3",
      "firstDiscoveredAt": "2026-03-10T15:26:34.444Z",
      "lastDiscoveredAt": "2026-03-10T15:26:34.444Z",
      "sourceQuery": "site:facebook.com pickleball Bayawan City (Tulong) Negros Oriental",
      "title": "Rotaract Club Of Tolong - Bayawan City",
      "snippet": "Rotaract Club Of Tolong - Bayawan City added a new photo — in Canlaon City, Negros Oriental ... ❣️ 1st Rotary Club of Tolong Pickleball Tournament ...",
      "domain": "facebook.com",
      "relevanceScore": 15,
      "handedOffToScrapeAt": "2026-03-10T15:26:34.444Z"
    },
    "https://facebook.com/groups/142896755886772/posts/3547617638747983": {
      "canonicalUrl": "https://facebook.com/groups/142896755886772/posts/3547617638747983",
      "latestUrl": "https://www.facebook.com/groups/142896755886772/posts/3547617638747983/",
      "firstDiscoveredAt": "2026-03-10T15:26:34.444Z",
      "lastDiscoveredAt": "2026-03-10T15:26:34.444Z",
      "sourceQuery": "site:facebook.com pickleball Bayawan City (Tulong) Negros Oriental",
      "title": "Bayawan City, Negros Oriental - Facebook",
      "snippet": "NEW PICKLE BALL TSHIRT DESIGN Check out now ‼️ Pickleball OneMoreGame Full Sublimation T-Shirt | Shopee Philippines. S.SHOPEE.PH.",
      "domain": "facebook.com",
      "relevanceScore": 10,
      "handedOffToScrapeAt": null
    },
    "https://facebook.com/cheriescheesecakehouse/posts/our-vip-pica-pica-table-spread-during-the-3rd-dumaguete-baby-boys-pickle-ball-le/889593627167388": {
      "canonicalUrl": "https://facebook.com/cheriescheesecakehouse/posts/our-vip-pica-pica-table-spread-during-the-3rd-dumaguete-baby-boys-pickle-ball-le/889593627167388",
      "latestUrl": "https://www.facebook.com/cheriescheesecakehouse/posts/our-vip-pica-pica-table-spread-during-the-3rd-dumaguete-baby-boys-pickle-ball-le/889593627167388/",
      "firstDiscoveredAt": "2026-03-10T15:26:34.444Z",
      "lastDiscoveredAt": "2026-03-10T15:26:34.444Z",
      "sourceQuery": "site:facebook.com pickleball Bayawan City (Tulong) Negros Oriental",
      "title": "Our VIP Pica Pica Table Spread during the 3rd Dumaguete Baby ...",
      "snippet": "Our VIP Pica Pica Table Spread during the 3rd Dumaguete Baby Boys Pickle Ball League Many thanks to Cong. Janice Degamo, Cong.",
      "domain": "facebook.com",
      "relevanceScore": 2,
      "handedOffToScrapeAt": null
    },
    "https://facebook.com/100079243231623/photos/d41d8cd9/949049171079849": {
      "canonicalUrl": "https://facebook.com/100079243231623/photos/d41d8cd9/949049171079849",
      "latestUrl": "https://www.facebook.com/100079243231623/photos/d41d8cd9/949049171079849/",
      "firstDiscoveredAt": "2026-03-10T15:26:34.444Z",
      "lastDiscoveredAt": "2026-03-10T15:26:34.444Z",
      "sourceQuery": "site:facebook.com pickleball Bayawan City (Tulong) Negros Oriental",
      "title": "Bayawan City, Negros Oriental - Facebook",
      "snippet": "Super ganda at subrang malaking tulong po ang wakitos business.... ... Pickleball OneMoreGame Full Sublimation T- Shirt | Shopee Philippines. Buy ...",
      "domain": "facebook.com",
      "relevanceScore": 10,
      "handedOffToScrapeAt": null
    },
    "https://facebook.com/groups/142896755886772/posts/3546471082195972": {
      "canonicalUrl": "https://facebook.com/groups/142896755886772/posts/3546471082195972",
      "latestUrl": "https://www.facebook.com/groups/142896755886772/posts/3546471082195972/",
      "firstDiscoveredAt": "2026-03-10T15:26:34.444Z",
      "lastDiscoveredAt": "2026-03-10T15:26:34.444Z",
      "sourceQuery": "site:facebook.com pickleball Bayawan City (Tulong) Negros Oriental",
      "title": "for take all ₱130 meet up Sunday 9-10 Am plaza bayawan - Facebook",
      "snippet": "for take all ₱130 meet up Sunday 9-10 Am plaza bayawan · Other posts · Join us Now ! · Ayungon, Neg Or wholesaler. · NEW PICKLE BALL TSHIRT DESIGN ...",
      "domain": "facebook.com",
      "relevanceScore": 2,
      "handedOffToScrapeAt": null
    },
    "https://facebook.com/groups/505965599867393/posts/2399790183818249": {
      "canonicalUrl": "https://facebook.com/groups/505965599867393/posts/2399790183818249",
      "latestUrl": "https://www.facebook.com/groups/505965599867393/posts/2399790183818249/",
      "firstDiscoveredAt": "2026-03-10T15:26:34.444Z",
      "lastDiscoveredAt": "2026-03-10T15:26:34.444Z",
      "sourceQuery": "site:facebook.com pickleball Bayawan City (Tulong) Negros Oriental",
      "title": "GIDEONS COURT in Dumaguete City now offers BAYAWAN CITY'S ...",
      "snippet": "You can contact them at 09395390143. They are open 24hrs daily. #dumaguete #dumaguetecity #gideons #gideonscourt #pickleball #negros # ...",
      "domain": "facebook.com",
      "relevanceScore": 10,
      "handedOffToScrapeAt": null
    },
    "https://facebook.com/groups/1205096034544328": {
      "canonicalUrl": "https://facebook.com/groups/1205096034544328",
      "latestUrl": "https://www.facebook.com/groups/1205096034544328/",
      "firstDiscoveredAt": "2026-03-10T15:26:34.444Z",
      "lastDiscoveredAt": "2026-03-10T15:26:34.444Z",
      "sourceQuery": "site:facebook.com \"Negros Oriental\" \"pickleball\"",
      "title": "NOPD - Negros Oriental Pickleball District | Facebook",
      "snippet": "NOPD - Negros Oriental Pickleball District. Join group. About this group ... Pickleball courts from a drone view look absolutely amazing! If you haven't ...",
      "domain": "facebook.com",
      "relevanceScore": 12,
      "handedOffToScrapeAt": null
    },
    "https://facebook.com/groups/1205096034544328/posts/1419555523098377": {
      "canonicalUrl": "https://facebook.com/groups/1205096034544328/posts/1419555523098377",
      "latestUrl": "https://www.facebook.com/groups/1205096034544328/posts/1419555523098377/",
      "firstDiscoveredAt": "2026-03-10T15:26:34.444Z",
      "lastDiscoveredAt": "2026-03-10T15:26:34.444Z",
      "sourceQuery": "site:facebook.com \"Negros Oriental\" \"pickleball\"",
      "title": "List of pickleball club organizers in Negros Oriental - Facebook",
      "snippet": "UPDATED LIST OF NOPD DUPR CLUB ORGANIZERS IN NEGROS ORIENTAL⚔️ Adelle Abalos | Dumaguete Baby Boys Pickleball Club Angeli Teves Singgo | TNLU ...",
      "domain": "facebook.com",
      "relevanceScore": 12,
      "handedOffToScrapeAt": null
    },
    "https://facebook.com/groups/1205096034544328/posts/1451711993216063": {
      "canonicalUrl": "https://facebook.com/groups/1205096034544328/posts/1451711993216063",
      "latestUrl": "https://www.facebook.com/groups/1205096034544328/posts/1451711993216063/",
      "firstDiscoveredAt": "2026-03-10T15:26:34.444Z",
      "lastDiscoveredAt": "2026-03-10T15:26:34.444Z",
      "sourceQuery": "site:facebook.com \"Negros Oriental\" \"pickleball\"",
      "title": "NOPD - Negros Oriental Pickleball District - Facebook",
      "snippet": "Reserve Friday afternoon OP ⏰ Fri, Mar 6 1:00 PM Reserve Pickleball Court Center RSVP: ... Looking for Pickleball meets in Negros Oriental, ...",
      "domain": "facebook.com",
      "relevanceScore": 12,
      "handedOffToScrapeAt": null
    },
    "https://facebook.com/groups/1205096034544328/posts/1452474419806487": {
      "canonicalUrl": "https://facebook.com/groups/1205096034544328/posts/1452474419806487",
      "latestUrl": "https://www.facebook.com/groups/1205096034544328/posts/1452474419806487/",
      "firstDiscoveredAt": "2026-03-10T15:26:34.444Z",
      "lastDiscoveredAt": "2026-03-10T15:26:34.444Z",
      "sourceQuery": "site:facebook.com \"Negros Oriental\" \"pickleball\"",
      "title": "NOPD - Negros Oriental Pickleball District - Facebook",
      "snippet": "Log in · NOPD - Negros Oriental Pickleball District. NOPD - Negros Oriental Pickleball District.",
      "domain": "facebook.com",
      "relevanceScore": 10,
      "handedOffToScrapeAt": null
    },
    "https://facebook.com/groups/1205096034544328/posts/1451600926560503": {
      "canonicalUrl": "https://facebook.com/groups/1205096034544328/posts/1451600926560503",
      "latestUrl": "https://www.facebook.com/groups/1205096034544328/posts/1451600926560503/",
      "firstDiscoveredAt": "2026-03-10T15:26:34.444Z",
      "lastDiscoveredAt": "2026-03-10T15:26:34.444Z",
      "sourceQuery": "site:facebook.com \"Negros Oriental\" \"pickleball\"",
      "title": "NOPD - Negros Oriental Pickleball District - Facebook",
      "snippet": "Everyone will be ranked... only top 220 players will be invited. Are you part of the TOP 220 BABY BOYS Pickleball Players in Negros Oriental?",
      "domain": "facebook.com",
      "relevanceScore": 10,
      "handedOffToScrapeAt": null
    },
    "https://facebook.com/groups/1205096034544328/posts/1380630140324249": {
      "canonicalUrl": "https://facebook.com/groups/1205096034544328/posts/1380630140324249",
      "latestUrl": "https://www.facebook.com/groups/1205096034544328/posts/1380630140324249/",
      "firstDiscoveredAt": "2026-03-10T15:26:34.444Z",
      "lastDiscoveredAt": "2026-03-10T15:26:34.444Z",
      "sourceQuery": "site:facebook.com \"Negros Oriental\" \"pickleball\"",
      "title": "Thoughts on forever intermediate player    JC - Facebook",
      "snippet": "Welcome to the RALLY HOUSE PICKLEBALL! We're dedicated to all things pickleball – the fastest- growing sport in Negros Oriental! Whether you're ...",
      "domain": "facebook.com",
      "relevanceScore": 10,
      "handedOffToScrapeAt": null
    },
    "https://facebook.com/p/Negros-Oriental-Pickleball-Club-61557985336286": {
      "canonicalUrl": "https://facebook.com/p/Negros-Oriental-Pickleball-Club-61557985336286",
      "latestUrl": "https://www.facebook.com/p/Negros-Oriental-Pickleball-Club-61557985336286/",
      "firstDiscoveredAt": "2026-03-10T15:26:34.444Z",
      "lastDiscoveredAt": "2026-03-10T15:26:34.444Z",
      "sourceQuery": "site:facebook.com \"Negros Oriental\" \"pickleball\"",
      "title": "Negros Oriental Pickleball Club | Dumaguete City - Facebook",
      "snippet": "Negros Oriental Pickleball Club, Dumaguete City. 1139 likes · 5 talking about this. Negros Oriental Pickleball Club is a non-partisan, non-business and...",
      "domain": "facebook.com",
      "relevanceScore": 15,
      "handedOffToScrapeAt": "2026-03-10T15:26:34.444Z"
    },
    "https://facebook.com/groups/1205096034544328/posts/1440912950962634": {
      "canonicalUrl": "https://facebook.com/groups/1205096034544328/posts/1440912950962634",
      "latestUrl": "https://www.facebook.com/groups/1205096034544328/posts/1440912950962634/",
      "firstDiscoveredAt": "2026-03-10T15:26:34.444Z",
      "lastDiscoveredAt": "2026-03-10T15:26:34.444Z",
      "sourceQuery": "site:facebook.com \"Negros Oriental\" \"pickleball\"",
      "title": "Join Negros Oriental pickleball district community - Facebook",
      "snippet": "OCR: NOPD NOPD NEGROS ORIENTAL PICKLEBALL DISTRICT 171 active 558 members Moreille Tatel Admin Communit nity ty vin ПГГО Welcome, ...",
      "domain": "facebook.com",
      "relevanceScore": 10,
      "handedOffToScrapeAt": null
    },
    "https://facebook.com/groups/1205096034544328/posts/1449718153415447": {
      "canonicalUrl": "https://facebook.com/groups/1205096034544328/posts/1449718153415447",
      "latestUrl": "https://www.facebook.com/groups/1205096034544328/posts/1449718153415447/",
      "firstDiscoveredAt": "2026-03-10T15:26:34.444Z",
      "lastDiscoveredAt": "2026-03-10T15:26:34.444Z",
      "sourceQuery": "site:facebook.com \"Negros Oriental\" \"pickleball\"",
      "title": "NOPD - Negros Oriental Pickleball District - Facebook",
      "snippet": "NOPD - Negros Oriental Pickleball District. NOPD - Negros Oriental Pickleball District. Danice Kaye Fanio󰞋3h󰞋󱟠. 󳄫. Pickleball Market Philippines ...",
      "domain": "facebook.com",
      "relevanceScore": 10,
      "handedOffToScrapeAt": null
    },
    "https://facebook.com/groups/1205096034544328/posts/1365053751881888": {
      "canonicalUrl": "https://facebook.com/groups/1205096034544328/posts/1365053751881888",
      "latestUrl": "https://www.facebook.com/groups/1205096034544328/posts/1365053751881888/",
      "firstDiscoveredAt": "2026-03-10T15:26:34.444Z",
      "lastDiscoveredAt": "2026-03-10T15:26:34.444Z",
      "sourceQuery": "site:facebook.com \"Negros Oriental\" \"pickleball\"",
      "title": "Pickleball clubs in Negros Oriental? - Facebook",
      "snippet": "NOPD - Negros Oriental Pickleball District. Admin Moreille Tatel󰞋Nov ... Tanawon nato unsa na kadaghana ang pickleball clubs sa Dumaguete/Negros ...",
      "domain": "facebook.com",
      "relevanceScore": 12,
      "handedOffToScrapeAt": null
    }
  }
}
